{
    "type":"facebook_post",
    "data":{
        "url":"https://www.facebook.com/thecodinglove/posts/587630088063200",
        "meta":{
            "provider_url":"https://www.facebook.com",
            "success":true,
            "url":"https://www.facebook.com/thecodinglove/posts/587630088063200",
            "html":"<div id=\"fb-root\"></div>\n<script>(function(d, s, id) {\n  var js, fjs = d.getElementsByTagName(s)[0];\n  if (d.getElementById(id)) return;\n  js = d.createElement(s); js.id = id;\n  js.src = 'https://connect.facebook.net/en_US/sdk.js#xfbml=1&version=v2.12';\n  fjs.parentNode.insertBefore(js, fjs);\n}(document, 'script', 'facebook-jssdk'));</script><div class=\"fb-post\" data-href=\"https://www.facebook.com/thecodinglove/posts/587630088063200\" data-width=\"552\"><blockquote cite=\"https://www.facebook.com/thecodinglove/posts/587630088063200\" class=\"fb-xfbml-parse-ignore\"><p>When the demo doesn&#039;t go as expected</p>Posted by <a href=\"https://www.facebook.com/thecodinglove/\">The coding love</a> on&nbsp;<a href=\"https://www.facebook.com/thecodinglove/posts/587630088063200\">Thursday, March 10, 2016</a></blockquote></div>",
            "author_name":"The coding love",
            "height":null,
            "width":552,
            "version":"1.0",
            "author_url":"https://www.facebook.com/thecodinglove/",
            "provider_name":"Facebook"
        }
    },
    "id":"6eb4e999-2b81-9b92-c7de-d76293d274f1"
}
